commoditpriceyapi/__init__.py
commoditpriceyapi/client.py
commoditypriceapi-0.2.0.dist-info/licenses/License
commoditypriceapi-0.2.0.dist-info/METADATA
commoditypriceapi-0.2.0.dist-info/WHEEL
commoditypriceapi-0.2.0.dist-info/top_level.txt
commoditypriceapi-0.2.0.dist-info/RECORD
