Metadata-Version: 2.4
Name: commoditypriceapi
Version: 0.2.0
Summary: Python SDK for CommodityPriceAPI
Author-email: Your Name <you@example.com>
License: MIT
Requires-Python: >=3.7
License-File: License
Requires-Dist: requests>=2.28
Dynamic: license-file
